ai4ao/__init__.py
ai4ao/utils.py
ai4ao/models/__init__.py
ai4ao/models/models.py
ai4ao/models/sklearn_model.py
ai4ao-0.1.8.dist-info/METADATA
ai4ao-0.1.8.dist-info/WHEEL
ai4ao-0.1.8.dist-info/top_level.txt
ai4ao-0.1.8.dist-info/RECORD
