Metadata-Version: 2.1
Name: ai4ao
Version: 0.1.8
Summary: UNKNOWN
Home-page: https://gitlab.com/selvai/ai4ao
Author: Selvakumar Ulaganathan
Author-email: flag.selva@gmail.com
License: UNKNOWN
Project-URL: Documentation, https://selvai.gitlab.io/ai4ao/
Project-URL: Developer, https://www.selvai.com
Keywords: Anomaly Detection,Outlier Detection
Platform: UNKNOWN
Classifier: Topic :: Scientific/Engineering :: Artificial Intelligence
Requires-Python: >=3.6
Requires-Dist: matplotlib
Requires-Dist: numpy
Requires-Dist: scipy
Requires-Dist: pandas
Requires-Dist: PyYAML
Requires-Dist: scikit-learn
